keepalived_config/__init__.py
keepalived_config/keepalived_config.py
keepalived_config/keepalived_config_block.py
keepalived_config/keepalived_config_comment.py
keepalived_config/keepalived_config_constants.py
keepalived_config/keepalived_config_param.py
keepalived_config/keepalived_config_parser.py
keepalived_config-0.2.1.dist-info/licenses/LICENSE
keepalived_config-0.2.1.dist-info/METADATA
keepalived_config-0.2.1.dist-info/WHEEL
keepalived_config-0.2.1.dist-info/top_level.txt
keepalived_config-0.2.1.dist-info/RECORD
