Metadata-Version: 2.4
Name: keepalived-config
Version: 0.2.1
Home-page: https://github.com/Slinred/keepalived-config
Author: Nils Weyand
License: GNU GENERAL PUBLIC LICENSE
Requires-Python: >=3.10
License-File: LICENSE
Dynamic: author
Dynamic: description
Dynamic: description-content-type
Dynamic: home-page
Dynamic: license
Dynamic: license-file
Dynamic: requires-python
